{
  "data": [
    {
      "variable": "N",
      "stat": "336",
      "colgroup1": "colgroup1",
      "colgroup1_level": "PBO N = 334",
      "colgroup2": "colgroup2",
      "colgroup2_level": "PBO N = 334"
    },
    {
      "variable": "N",
      "stat": "334",
      "colgroup1": "colgroup1",
      "colgroup1_level": "PBO N = 334",
      "colgroup2": "colgroup2",
      "colgroup2_level": "Total N = 670"
    },
    {
      "variable": "N",
      "stat": "670",
      "colgroup1": "colgroup1",
      "colgroup1_level": "Total N = 670",
      "colgroup2": "colgroup2",
      "colgroup2_level": ""
    },
    {
      "variable": "MEAN",
      "stat": "51.7",
      "colgroup1": "colgroup1",
      "colgroup1_level": "PBO N = 334",
      "colgroup2": "colgroup2",
      "colgroup2_level": "PBO N = 334"
    },
    {
      "variable": "MEAN",
      "stat": "52.3",
      "colgroup1": "colgroup1",
      "colgroup1_level": "PBO N = 334",
      "colgroup2": "colgroup2",
      "colgroup2_level": "Total N = 670"
    },
    {
      "variable": "MEAN",
      "stat": "52.0",
      "colgroup1": "colgroup1",
      "colgroup1_level": "Total N = 670",
      "colgroup2": "colgroup2",
      "colgroup2_level": ""
    },
    {
      "variable": "SD",
      "stat": "12.52",
      "colgroup1": "colgroup1",
      "colgroup1_level": "PBO N = 334",
      "colgroup2": "colgroup2",
      "colgroup2_level": "PBO N = 334"
    },
    {
      "variable": "SD",
      "stat": "12.32",
      "colgroup1": "colgroup1",
      "colgroup1_level": "PBO N = 334",
      "colgroup2": "colgroup2",
      "colgroup2_level": "Total N = 670"
    },
    {
      "variable": "SD",
      "stat": "12.41",
      "colgroup1": "colgroup1",
      "colgroup1_level": "Total N = 670",
      "colgroup2": "colgroup2",
      "colgroup2_level": ""
    },
    {
      "variable": "MEDIAN",
      "stat": "52.0",
      "colgroup1": "colgroup1",
      "colgroup1_level": "PBO N = 334",
      "colgroup2": "colgroup2",
      "colgroup2_level": "PBO N = 334"
    },
    {
      "variable": "MEDIAN",
      "stat": "52.0",
      "colgroup1": "colgroup1",
      "colgroup1_level": "PBO N = 334",
      "colgroup2": "colgroup2",
      "colgroup2_level": "Total N = 670"
    },
    {
      "variable": "MEDIAN",
      "stat": "52.0",
      "colgroup1": "colgroup1",
      "colgroup1_level": "Total N = 670",
      "colgroup2": "colgroup2",
      "colgroup2_level": ""
    },
    {
      "variable": "Q1, Q3",
      "stat": "43.0, 60.0",
      "colgroup1": "colgroup1",
      "colgroup1_level": "PBO N = 334",
      "colgroup2": "colgroup2",
      "colgroup2_level": "PBO N = 334"
    },
    {
      "variable": "Q1, Q3",
      "stat": "45.0, 61.0",
      "colgroup1": "colgroup1",
      "colgroup1_level": "PBO N = 334",
      "colgroup2": "colgroup2",
      "colgroup2_level": "Total N = 670"
    },
    {
      "variable": "Q1, Q3",
      "stat": "44.0, 61.0",
      "colgroup1": "colgroup1",
      "colgroup1_level": "Total N = 670",
      "colgroup2": "colgroup2",
      "colgroup2_level": ""
    },
    {
      "variable": "MIN, MAX",
      "stat": "23, 86",
      "colgroup1": "colgroup1",
      "colgroup1_level": "PBO N = 334",
      "colgroup2": "colgroup2",
      "colgroup2_level": "PBO N = 334"
    },
    {
      "variable": "MIN, MAX",
      "stat": "21, 83",
      "colgroup1": "colgroup1",
      "colgroup1_level": "PBO N = 334",
      "colgroup2": "colgroup2",
      "colgroup2_level": "Total N = 670"
    },
    {
      "variable": "MIN, MAX",
      "stat": "21, 86",
      "colgroup1": "colgroup1",
      "colgroup1_level": "Total N = 670",
      "colgroup2": "colgroup2",
      "colgroup2_level": ""
    },
    {
      "variable": "<45",
      "stat": "98 ( 29.2)",
      "colgroup1": "colgroup1",
      "colgroup1_level": "PBO N = 334",
      "colgroup2": "colgroup2",
      "colgroup2_level": "PBO N = 334"
    },
    {
      "variable": "<45",
      "stat": "83 ( 24.9)",
      "colgroup1": "colgroup1",
      "colgroup1_level": "PBO N = 334",
      "colgroup2": "colgroup2",
      "colgroup2_level": "Total N = 670"
    },
    {
      "variable": "<45",
      "stat": "181 ( 27.0)",
      "colgroup1": "colgroup1",
      "colgroup1_level": "Total N = 670",
      "colgroup2": "colgroup2",
      "colgroup2_level": ""
    },
    {
      "variable": "45 - 65",
      "stat": "187 ( 55.7)",
      "colgroup1": "colgroup1",
      "colgroup1_level": "PBO N = 334",
      "colgroup2": "colgroup2",
      "colgroup2_level": "PBO N = 334"
    },
    {
      "variable": "45 - 65",
      "stat": "194 ( 58.1)",
      "colgroup1": "colgroup1",
      "colgroup1_level": "PBO N = 334",
      "colgroup2": "colgroup2",
      "colgroup2_level": "Total N = 670"
    },
    {
      "variable": "45 - 65",
      "stat": "381 ( 56.9)",
      "colgroup1": "colgroup1",
      "colgroup1_level": "Total N = 670",
      "colgroup2": "colgroup2",
      "colgroup2_level": ""
    },
    {
      "variable": ">=65",
      "stat": "51 ( 15.2)",
      "colgroup1": "colgroup1",
      "colgroup1_level": "PBO N = 334",
      "colgroup2": "colgroup2",
      "colgroup2_level": "PBO N = 334"
    },
    {
      "variable": ">=65",
      "stat": "57 ( 17.1)",
      "colgroup1": "colgroup1",
      "colgroup1_level": "PBO N = 334",
      "colgroup2": "colgroup2",
      "colgroup2_level": "Total N = 670"
    },
    {
      "variable": ">=65",
      "stat": "108 ( 16.1)",
      "colgroup1": "colgroup1",
      "colgroup1_level": "Total N = 670",
      "colgroup2": "colgroup2",
      "colgroup2_level": ""
    },
    {
      "variable": "MALE",
      "stat": "172 ( 51.2)",
      "colgroup1": "colgroup1",
      "colgroup1_level": "PBO N = 334",
      "colgroup2": "colgroup2",
      "colgroup2_level": "PBO N = 334"
    },
    {
      "variable": "MALE",
      "stat": "164 ( 49.1)",
      "colgroup1": "colgroup1",
      "colgroup1_level": "PBO N = 334",
      "colgroup2": "colgroup2",
      "colgroup2_level": "Total N = 670"
    },
    {
      "variable": "MALE",
      "stat": "336 ( 50.1)",
      "colgroup1": "colgroup1",
      "colgroup1_level": "Total N = 670",
      "colgroup2": "colgroup2",
      "colgroup2_level": ""
    },
    {
      "variable": "FEMALE",
      "stat": "164 ( 48.8)",
      "colgroup1": "colgroup1",
      "colgroup1_level": "PBO N = 334",
      "colgroup2": "colgroup2",
      "colgroup2_level": "PBO N = 334"
    },
    {
      "variable": "FEMALE",
      "stat": "170 ( 50.9)",
      "colgroup1": "colgroup1",
      "colgroup1_level": "PBO N = 334",
      "colgroup2": "colgroup2",
      "colgroup2_level": "Total N = 670"
    },
    {
      "variable": "FEMALE",
      "stat": "334 ( 49.9)",
      "colgroup1": "colgroup1",
      "colgroup1_level": "Total N = 670",
      "colgroup2": "colgroup2",
      "colgroup2_level": ""
    },
    {
      "variable": "Protocol: IM011054",
      "stat": "Protocol: IM011054",
      "colgroup1": "colgroup1",
      "colgroup1_level": "PBO N = 334",
      "colgroup2": "colgroup2",
      "colgroup2_level": "PBO N = 334"
    },
    {
      "variable": "Protocol: IM011054",
      "stat": "Protocol: IM011054Page PAGE of NUMPAGES",
      "colgroup1": "colgroup1",
      "colgroup1_level": "PBO N = 334",
      "colgroup2": "colgroup2",
      "colgroup2_level": "Total N = 670"
    },
    {
      "variable": "Protocol: IM011054",
      "stat": "Protocol: IM011054Page PAGE of NUMPAGES",
      "colgroup1": "colgroup1",
      "colgroup1_level": "Total N = 670",
      "colgroup2": "colgroup2",
      "colgroup2_level": ""
    },
    {
      "variable": "WHITE",
      "stat": "263 ( 78.3)",
      "colgroup1": "colgroup1",
      "colgroup1_level": "PBO N = 334",
      "colgroup2": "colgroup2",
      "colgroup2_level": "PBO N = 334"
    },
    {
      "variable": "WHITE",
      "stat": "279 ( 83.5)",
      "colgroup1": "colgroup1",
      "colgroup1_level": "PBO N = 334",
      "colgroup2": "colgroup2",
      "colgroup2_level": "Total N = 670"
    },
    {
      "variable": "WHITE",
      "stat": "542 ( 80.9)",
      "colgroup1": "colgroup1",
      "colgroup1_level": "Total N = 670",
      "colgroup2": "colgroup2",
      "colgroup2_level": ""
    },
    {
      "variable": "BLACK OR AFRICAN AMERICAN",
      "stat": "4 ( 1.2)",
      "colgroup1": "colgroup1",
      "colgroup1_level": "PBO N = 334",
      "colgroup2": "colgroup2",
      "colgroup2_level": "PBO N = 334"
    },
    {
      "variable": "BLACK OR AFRICAN AMERICAN",
      "stat": "1 ( 0.3)",
      "colgroup1": "colgroup1",
      "colgroup1_level": "PBO N = 334",
      "colgroup2": "colgroup2",
      "colgroup2_level": "Total N = 670"
    },
    {
      "variable": "BLACK OR AFRICAN AMERICAN",
      "stat": "5 ( 0.7)",
      "colgroup1": "colgroup1",
      "colgroup1_level": "Total N = 670",
      "colgroup2": "colgroup2",
      "colgroup2_level": ""
    },
    {
      "variable": "AMERICAN INDIAN OR ALASKA NATIVE",
      "stat": "17 ( 5.1)",
      "colgroup1": "colgroup1",
      "colgroup1_level": "PBO N = 334",
      "colgroup2": "colgroup2",
      "colgroup2_level": "PBO N = 334"
    },
    {
      "variable": "AMERICAN INDIAN OR ALASKA NATIVE",
      "stat": "19 ( 5.7)",
      "colgroup1": "colgroup1",
      "colgroup1_level": "PBO N = 334",
      "colgroup2": "colgroup2",
      "colgroup2_level": "Total N = 670"
    },
    {
      "variable": "AMERICAN INDIAN OR ALASKA NATIVE",
      "stat": "36 ( 5.4)",
      "colgroup1": "colgroup1",
      "colgroup1_level": "Total N = 670",
      "colgroup2": "colgroup2",
      "colgroup2_level": ""
    },
    {
      "variable": "OTHER",
      "stat": "27 ( 8.0)",
      "colgroup1": "colgroup1",
      "colgroup1_level": "PBO N = 334",
      "colgroup2": "colgroup2",
      "colgroup2_level": "PBO N = 334"
    },
    {
      "variable": "OTHER",
      "stat": "21 ( 6.3)",
      "colgroup1": "colgroup1",
      "colgroup1_level": "PBO N = 334",
      "colgroup2": "colgroup2",
      "colgroup2_level": "Total N = 670"
    },
    {
      "variable": "OTHER",
      "stat": "48 ( 7.2)",
      "colgroup1": "colgroup1",
      "colgroup1_level": "Total N = 670",
      "colgroup2": "colgroup2",
      "colgroup2_level": ""
    },
    {
      "variable": "ASIAN",
      "stat": "25 ( 7.4)",
      "colgroup1": "colgroup1",
      "colgroup1_level": "PBO N = 334",
      "colgroup2": "colgroup2",
      "colgroup2_level": "PBO N = 334"
    },
    {
      "variable": "ASIAN",
      "stat": "14 ( 4.2)",
      "colgroup1": "colgroup1",
      "colgroup1_level": "PBO N = 334",
      "colgroup2": "colgroup2",
      "colgroup2_level": "Total N = 670"
    },
    {
      "variable": "ASIAN",
      "stat": "39 ( 5.8)",
      "colgroup1": "colgroup1",
      "colgroup1_level": "Total N = 670",
      "colgroup2": "colgroup2",
      "colgroup2_level": ""
    },
    {
      "variable": "~~CHINESE",
      "stat": "24 ( 7.1)",
      "colgroup1": "colgroup1",
      "colgroup1_level": "PBO N = 334",
      "colgroup2": "colgroup2",
      "colgroup2_level": "PBO N = 334"
    },
    {
      "variable": "~~CHINESE",
      "stat": "14 ( 4.2)",
      "colgroup1": "colgroup1",
      "colgroup1_level": "PBO N = 334",
      "colgroup2": "colgroup2",
      "colgroup2_level": "Total N = 670"
    },
    {
      "variable": "~~CHINESE",
      "stat": "38 ( 5.7)",
      "colgroup1": "colgroup1",
      "colgroup1_level": "Total N = 670",
      "colgroup2": "colgroup2",
      "colgroup2_level": ""
    },
    {
      "variable": "~~ASIAN OTHER",
      "stat": "1 ( 0.3)",
      "colgroup1": "colgroup1",
      "colgroup1_level": "PBO N = 334",
      "colgroup2": "colgroup2",
      "colgroup2_level": "PBO N = 334"
    },
    {
      "variable": "~~ASIAN OTHER",
      "stat": "0",
      "colgroup1": "colgroup1",
      "colgroup1_level": "PBO N = 334",
      "colgroup2": "colgroup2",
      "colgroup2_level": "Total N = 670"
    },
    {
      "variable": "~~ASIAN OTHER",
      "stat": "1 ( 0.1)",
      "colgroup1": "colgroup1",
      "colgroup1_level": "Total N = 670",
      "colgroup2": "colgroup2",
      "colgroup2_level": ""
    },
    {
      "variable": "HISPANIC OR LATINO",
      "stat": "101 ( 30.1)",
      "colgroup1": "colgroup1",
      "colgroup1_level": "PBO N = 334",
      "colgroup2": "colgroup2",
      "colgroup2_level": "PBO N = 334"
    },
    {
      "variable": "HISPANIC OR LATINO",
      "stat": "94 ( 28.1)",
      "colgroup1": "colgroup1",
      "colgroup1_level": "PBO N = 334",
      "colgroup2": "colgroup2",
      "colgroup2_level": "Total N = 670"
    },
    {
      "variable": "HISPANIC OR LATINO",
      "stat": "195 ( 29.1)",
      "colgroup1": "colgroup1",
      "colgroup1_level": "Total N = 670",
      "colgroup2": "colgroup2",
      "colgroup2_level": ""
    },
    {
      "variable": "NOT HISPANIC OR LATINO",
      "stat": "165 ( 49.1)",
      "colgroup1": "colgroup1",
      "colgroup1_level": "PBO N = 334",
      "colgroup2": "colgroup2",
      "colgroup2_level": "PBO N = 334"
    },
    {
      "variable": "NOT HISPANIC OR LATINO",
      "stat": "165 ( 49.4)",
      "colgroup1": "colgroup1",
      "colgroup1_level": "PBO N = 334",
      "colgroup2": "colgroup2",
      "colgroup2_level": "Total N = 670"
    },
    {
      "variable": "NOT HISPANIC OR LATINO",
      "stat": "330 ( 49.3)",
      "colgroup1": "colgroup1",
      "colgroup1_level": "Total N = 670",
      "colgroup2": "colgroup2",
      "colgroup2_level": ""
    },
    {
      "variable": "NOT REPORTED",
      "stat": "70 ( 20.8)",
      "colgroup1": "colgroup1",
      "colgroup1_level": "PBO N = 334",
      "colgroup2": "colgroup2",
      "colgroup2_level": "PBO N = 334"
    },
    {
      "variable": "NOT REPORTED",
      "stat": "75 ( 22.5)",
      "colgroup1": "colgroup1",
      "colgroup1_level": "PBO N = 334",
      "colgroup2": "colgroup2",
      "colgroup2_level": "Total N = 670"
    },
    {
      "variable": "NOT REPORTED",
      "stat": "145 ( 21.6)",
      "colgroup1": "colgroup1",
      "colgroup1_level": "Total N = 670",
      "colgroup2": "colgroup2",
      "colgroup2_level": ""
    },
    {
      "variable": "NORTH AMERICA",
      "stat": "51 ( 15.2)",
      "colgroup1": "colgroup1",
      "colgroup1_level": "PBO N = 334",
      "colgroup2": "colgroup2",
      "colgroup2_level": "PBO N = 334"
    },
    {
      "variable": "NORTH AMERICA",
      "stat": "50 ( 15.0)",
      "colgroup1": "colgroup1",
      "colgroup1_level": "PBO N = 334",
      "colgroup2": "colgroup2",
      "colgroup2_level": "Total N = 670"
    },
    {
      "variable": "NORTH AMERICA",
      "stat": "101 ( 15.1)",
      "colgroup1": "colgroup1",
      "colgroup1_level": "Total N = 670",
      "colgroup2": "colgroup2",
      "colgroup2_level": ""
    },
    {
      "variable": "MEXICO",
      "stat": "32 ( 9.5)",
      "colgroup1": "colgroup1",
      "colgroup1_level": "PBO N = 334",
      "colgroup2": "colgroup2",
      "colgroup2_level": "PBO N = 334"
    },
    {
      "variable": "MEXICO",
      "stat": "26 ( 7.8)",
      "colgroup1": "colgroup1",
      "colgroup1_level": "PBO N = 334",
      "colgroup2": "colgroup2",
      "colgroup2_level": "Total N = 670"
    },
    {
      "variable": "MEXICO",
      "stat": "58 ( 8.7)",
      "colgroup1": "colgroup1",
      "colgroup1_level": "Total N = 670",
      "colgroup2": "colgroup2",
      "colgroup2_level": ""
    },
    {
      "variable": "UNITED STATES OF AMERICA",
      "stat": "19 ( 5.7)",
      "colgroup1": "colgroup1",
      "colgroup1_level": "PBO N = 334",
      "colgroup2": "colgroup2",
      "colgroup2_level": "PBO N = 334"
    },
    {
      "variable": "UNITED STATES OF AMERICA",
      "stat": "24 ( 7.2)",
      "colgroup1": "colgroup1",
      "colgroup1_level": "PBO N = 334",
      "colgroup2": "colgroup2",
      "colgroup2_level": "Total N = 670"
    },
    {
      "variable": "UNITED STATES OF AMERICA",
      "stat": "43 ( 6.4)",
      "colgroup1": "colgroup1",
      "colgroup1_level": "Total N = 670",
      "colgroup2": "colgroup2",
      "colgroup2_level": ""
    },
    {
      "variable": "SOUTH/LATIN AMERICA",
      "stat": "88 ( 26.2)",
      "colgroup1": "colgroup1",
      "colgroup1_level": "PBO N = 334",
      "colgroup2": "colgroup2",
      "colgroup2_level": "PBO N = 334"
    },
    {
      "variable": "SOUTH/LATIN AMERICA",
      "stat": "97 ( 29.0)",
      "colgroup1": "colgroup1",
      "colgroup1_level": "PBO N = 334",
      "colgroup2": "colgroup2",
      "colgroup2_level": "Total N = 670"
    },
    {
      "variable": "SOUTH/LATIN AMERICA",
      "stat": "185 ( 27.6)",
      "colgroup1": "colgroup1",
      "colgroup1_level": "Total N = 670",
      "colgroup2": "colgroup2",
      "colgroup2_level": ""
    },
    {
      "variable": "ARGENTINA",
      "stat": "36 ( 10.7)",
      "colgroup1": "colgroup1",
      "colgroup1_level": "PBO N = 334",
      "colgroup2": "colgroup2",
      "colgroup2_level": "PBO N = 334"
    },
    {
      "variable": "ARGENTINA",
      "stat": "38 ( 11.4)",
      "colgroup1": "colgroup1",
      "colgroup1_level": "PBO N = 334",
      "colgroup2": "colgroup2",
      "colgroup2_level": "Total N = 670"
    },
    {
      "variable": "ARGENTINA",
      "stat": "74 ( 11.0)",
      "colgroup1": "colgroup1",
      "colgroup1_level": "Total N = 670",
      "colgroup2": "colgroup2",
      "colgroup2_level": ""
    },
    {
      "variable": "BRAZIL",
      "stat": "15 ( 4.5)",
      "colgroup1": "colgroup1",
      "colgroup1_level": "PBO N = 334",
      "colgroup2": "colgroup2",
      "colgroup2_level": "PBO N = 334"
    },
    {
      "variable": "BRAZIL",
      "stat": "9 ( 2.7)",
      "colgroup1": "colgroup1",
      "colgroup1_level": "PBO N = 334",
      "colgroup2": "colgroup2",
      "colgroup2_level": "Total N = 670"
    },
    {
      "variable": "BRAZIL",
      "stat": "24 ( 3.6)",
      "colgroup1": "colgroup1",
      "colgroup1_level": "Total N = 670",
      "colgroup2": "colgroup2",
      "colgroup2_level": ""
    },
    {
      "variable": "CHILE",
      "stat": "26 ( 7.7)",
      "colgroup1": "colgroup1",
      "colgroup1_level": "PBO N = 334",
      "colgroup2": "colgroup2",
      "colgroup2_level": "PBO N = 334"
    },
    {
      "variable": "CHILE",
      "stat": "38 ( 11.4)",
      "colgroup1": "colgroup1",
      "colgroup1_level": "PBO N = 334",
      "colgroup2": "colgroup2",
      "colgroup2_level": "Total N = 670"
    },
    {
      "variable": "CHILE",
      "stat": "64 ( 9.6)",
      "colgroup1": "colgroup1",
      "colgroup1_level": "Total N = 670",
      "colgroup2": "colgroup2",
      "colgroup2_level": ""
    },
    {
      "variable": "COLOMBIA",
      "stat": "11 ( 3.3)",
      "colgroup1": "colgroup1",
      "colgroup1_level": "PBO N = 334",
      "colgroup2": "colgroup2",
      "colgroup2_level": "PBO N = 334"
    },
    {
      "variable": "COLOMBIA",
      "stat": "12 ( 3.6)",
      "colgroup1": "colgroup1",
      "colgroup1_level": "PBO N = 334",
      "colgroup2": "colgroup2",
      "colgroup2_level": "Total N = 670"
    },
    {
      "variable": "COLOMBIA",
      "stat": "23 ( 3.4)",
      "colgroup1": "colgroup1",
      "colgroup1_level": "Total N = 670",
      "colgroup2": "colgroup2",
      "colgroup2_level": ""
    },
    {
      "variable": "Protocol: IM011054",
      "stat": "Protocol: IM011054",
      "colgroup1": "colgroup1",
      "colgroup1_level": "PBO N = 334",
      "colgroup2": "colgroup2",
      "colgroup2_level": "PBO N = 334"
    },
    {
      "variable": "Protocol: IM011054",
      "stat": "Protocol: IM011054Page PAGE of NUMPAGES",
      "colgroup1": "colgroup1",
      "colgroup1_level": "PBO N = 334",
      "colgroup2": "colgroup2",
      "colgroup2_level": "Total N = 670"
    },
    {
      "variable": "Protocol: IM011054",
      "stat": "Protocol: IM011054Page PAGE of NUMPAGES",
      "colgroup1": "colgroup1",
      "colgroup1_level": "Total N = 670",
      "colgroup2": "colgroup2",
      "colgroup2_level": ""
    },
    {
      "variable": "EUROPE",
      "stat": "171 ( 50.9)",
      "colgroup1": "colgroup1",
      "colgroup1_level": "PBO N = 334",
      "colgroup2": "colgroup2",
      "colgroup2_level": "PBO N = 334"
    },
    {
      "variable": "EUROPE",
      "stat": "172 ( 51.5)",
      "colgroup1": "colgroup1",
      "colgroup1_level": "PBO N = 334",
      "colgroup2": "colgroup2",
      "colgroup2_level": "Total N = 670"
    },
    {
      "variable": "EUROPE",
      "stat": "343 ( 51.2)",
      "colgroup1": "colgroup1",
      "colgroup1_level": "Total N = 670",
      "colgroup2": "colgroup2",
      "colgroup2_level": ""
    },
    {
      "variable": "BULGARIA",
      "stat": "12 ( 3.6)",
      "colgroup1": "colgroup1",
      "colgroup1_level": "PBO N = 334",
      "colgroup2": "colgroup2",
      "colgroup2_level": "PBO N = 334"
    },
    {
      "variable": "BULGARIA",
      "stat": "14 ( 4.2)",
      "colgroup1": "colgroup1",
      "colgroup1_level": "PBO N = 334",
      "colgroup2": "colgroup2",
      "colgroup2_level": "Total N = 670"
    },
    {
      "variable": "BULGARIA",
      "stat": "26 ( 3.9)",
      "colgroup1": "colgroup1",
      "colgroup1_level": "Total N = 670",
      "colgroup2": "colgroup2",
      "colgroup2_level": ""
    },
    {
      "variable": "CZECHIA",
      "stat": "6 ( 1.8)",
      "colgroup1": "colgroup1",
      "colgroup1_level": "PBO N = 334",
      "colgroup2": "colgroup2",
      "colgroup2_level": "PBO N = 334"
    },
    {
      "variable": "CZECHIA",
      "stat": "7 ( 2.1)",
      "colgroup1": "colgroup1",
      "colgroup1_level": "PBO N = 334",
      "colgroup2": "colgroup2",
      "colgroup2_level": "Total N = 670"
    },
    {
      "variable": "CZECHIA",
      "stat": "13 ( 1.9)",
      "colgroup1": "colgroup1",
      "colgroup1_level": "Total N = 670",
      "colgroup2": "colgroup2",
      "colgroup2_level": ""
    },
    {
      "variable": "FINLAND",
      "stat": "4 ( 1.2)",
      "colgroup1": "colgroup1",
      "colgroup1_level": "PBO N = 334",
      "colgroup2": "colgroup2",
      "colgroup2_level": "PBO N = 334"
    },
    {
      "variable": "FINLAND",
      "stat": "1 ( 0.3)",
      "colgroup1": "colgroup1",
      "colgroup1_level": "PBO N = 334",
      "colgroup2": "colgroup2",
      "colgroup2_level": "Total N = 670"
    },
    {
      "variable": "FINLAND",
      "stat": "5 ( 0.7)",
      "colgroup1": "colgroup1",
      "colgroup1_level": "Total N = 670",
      "colgroup2": "colgroup2",
      "colgroup2_level": ""
    },
    {
      "variable": "FRANCE",
      "stat": "2 ( 0.6)",
      "colgroup1": "colgroup1",
      "colgroup1_level": "PBO N = 334",
      "colgroup2": "colgroup2",
      "colgroup2_level": "PBO N = 334"
    },
    {
      "variable": "FRANCE",
      "stat": "1 ( 0.3)",
      "colgroup1": "colgroup1",
      "colgroup1_level": "PBO N = 334",
      "colgroup2": "colgroup2",
      "colgroup2_level": "Total N = 670"
    },
    {
      "variable": "FRANCE",
      "stat": "3 ( 0.4)",
      "colgroup1": "colgroup1",
      "colgroup1_level": "Total N = 670",
      "colgroup2": "colgroup2",
      "colgroup2_level": ""
    },
    {
      "variable": "HUNGARY",
      "stat": "13 ( 3.9)",
      "colgroup1": "colgroup1",
      "colgroup1_level": "PBO N = 334",
      "colgroup2": "colgroup2",
      "colgroup2_level": "PBO N = 334"
    },
    {
      "variable": "HUNGARY",
      "stat": "10 ( 3.0)",
      "colgroup1": "colgroup1",
      "colgroup1_level": "PBO N = 334",
      "colgroup2": "colgroup2",
      "colgroup2_level": "Total N = 670"
    },
    {
      "variable": "HUNGARY",
      "stat": "23 ( 3.4)",
      "colgroup1": "colgroup1",
      "colgroup1_level": "Total N = 670",
      "colgroup2": "colgroup2",
      "colgroup2_level": ""
    },
    {
      "variable": "IRELAND",
      "stat": "1 ( 0.3)",
      "colgroup1": "colgroup1",
      "colgroup1_level": "PBO N = 334",
      "colgroup2": "colgroup2",
      "colgroup2_level": "PBO N = 334"
    },
    {
      "variable": "IRELAND",
      "stat": "0",
      "colgroup1": "colgroup1",
      "colgroup1_level": "PBO N = 334",
      "colgroup2": "colgroup2",
      "colgroup2_level": "Total N = 670"
    },
    {
      "variable": "IRELAND",
      "stat": "1 ( 0.1)",
      "colgroup1": "colgroup1",
      "colgroup1_level": "Total N = 670",
      "colgroup2": "colgroup2",
      "colgroup2_level": ""
    },
    {
      "variable": "ITALY",
      "stat": "1 ( 0.3)",
      "colgroup1": "colgroup1",
      "colgroup1_level": "PBO N = 334",
      "colgroup2": "colgroup2",
      "colgroup2_level": "PBO N = 334"
    },
    {
      "variable": "ITALY",
      "stat": "4 ( 1.2)",
      "colgroup1": "colgroup1",
      "colgroup1_level": "PBO N = 334",
      "colgroup2": "colgroup2",
      "colgroup2_level": "Total N = 670"
    },
    {
      "variable": "ITALY",
      "stat": "5 ( 0.7)",
      "colgroup1": "colgroup1",
      "colgroup1_level": "Total N = 670",
      "colgroup2": "colgroup2",
      "colgroup2_level": ""
    },
    {
      "variable": "POLAND",
      "stat": "103 ( 30.7)",
      "colgroup1": "colgroup1",
      "colgroup1_level": "PBO N = 334",
      "colgroup2": "colgroup2",
      "colgroup2_level": "PBO N = 334"
    },
    {
      "variable": "POLAND",
      "stat": "99 ( 29.6)",
      "colgroup1": "colgroup1",
      "colgroup1_level": "PBO N = 334",
      "colgroup2": "colgroup2",
      "colgroup2_level": "Total N = 670"
    },
    {
      "variable": "POLAND",
      "stat": "202 ( 30.1)",
      "colgroup1": "colgroup1",
      "colgroup1_level": "Total N = 670",
      "colgroup2": "colgroup2",
      "colgroup2_level": ""
    },
    {
      "variable": "ROMANIA",
      "stat": "13 ( 3.9)",
      "colgroup1": "colgroup1",
      "colgroup1_level": "PBO N = 334",
      "colgroup2": "colgroup2",
      "colgroup2_level": "PBO N = 334"
    },
    {
      "variable": "ROMANIA",
      "stat": "20 ( 6.0)",
      "colgroup1": "colgroup1",
      "colgroup1_level": "PBO N = 334",
      "colgroup2": "colgroup2",
      "colgroup2_level": "Total N = 670"
    },
    {
      "variable": "ROMANIA",
      "stat": "33 ( 4.9)",
      "colgroup1": "colgroup1",
      "colgroup1_level": "Total N = 670",
      "colgroup2": "colgroup2",
      "colgroup2_level": ""
    },
    {
      "variable": "RUSSIAN FEDERATION",
      "stat": "6 ( 1.8)",
      "colgroup1": "colgroup1",
      "colgroup1_level": "PBO N = 334",
      "colgroup2": "colgroup2",
      "colgroup2_level": "PBO N = 334"
    },
    {
      "variable": "RUSSIAN FEDERATION",
      "stat": "6 ( 1.8)",
      "colgroup1": "colgroup1",
      "colgroup1_level": "PBO N = 334",
      "colgroup2": "colgroup2",
      "colgroup2_level": "Total N = 670"
    },
    {
      "variable": "RUSSIAN FEDERATION",
      "stat": "12 ( 1.8)",
      "colgroup1": "colgroup1",
      "colgroup1_level": "Total N = 670",
      "colgroup2": "colgroup2",
      "colgroup2_level": ""
    },
    {
      "variable": "SPAIN",
      "stat": "6 ( 1.8)",
      "colgroup1": "colgroup1",
      "colgroup1_level": "PBO N = 334",
      "colgroup2": "colgroup2",
      "colgroup2_level": "PBO N = 334"
    },
    {
      "variable": "SPAIN",
      "stat": "9 ( 2.7)",
      "colgroup1": "colgroup1",
      "colgroup1_level": "PBO N = 334",
      "colgroup2": "colgroup2",
      "colgroup2_level": "Total N = 670"
    },
    {
      "variable": "SPAIN",
      "stat": "15 ( 2.2)",
      "colgroup1": "colgroup1",
      "colgroup1_level": "Total N = 670",
      "colgroup2": "colgroup2",
      "colgroup2_level": ""
    },
    {
      "variable": "ASIA",
      "stat": "25 ( 7.4)",
      "colgroup1": "colgroup1",
      "colgroup1_level": "PBO N = 334",
      "colgroup2": "colgroup2",
      "colgroup2_level": "PBO N = 334"
    },
    {
      "variable": "ASIA",
      "stat": "13 ( 3.9)",
      "colgroup1": "colgroup1",
      "colgroup1_level": "PBO N = 334",
      "colgroup2": "colgroup2",
      "colgroup2_level": "Total N = 670"
    },
    {
      "variable": "ASIA",
      "stat": "38 ( 5.7)",
      "colgroup1": "colgroup1",
      "colgroup1_level": "Total N = 670",
      "colgroup2": "colgroup2",
      "colgroup2_level": ""
    },
    {
      "variable": "CHINA",
      "stat": "15 ( 4.5)",
      "colgroup1": "colgroup1",
      "colgroup1_level": "PBO N = 334",
      "colgroup2": "colgroup2",
      "colgroup2_level": "PBO N = 334"
    },
    {
      "variable": "CHINA",
      "stat": "7 ( 2.1)",
      "colgroup1": "colgroup1",
      "colgroup1_level": "PBO N = 334",
      "colgroup2": "colgroup2",
      "colgroup2_level": "Total N = 670"
    },
    {
      "variable": "CHINA",
      "stat": "22 ( 3.3)",
      "colgroup1": "colgroup1",
      "colgroup1_level": "Total N = 670",
      "colgroup2": "colgroup2",
      "colgroup2_level": ""
    },
    {
      "variable": "TAIWAN, PROVINCE OF CHINA",
      "stat": "10 ( 3.0)",
      "colgroup1": "colgroup1",
      "colgroup1_level": "PBO N = 334",
      "colgroup2": "colgroup2",
      "colgroup2_level": "PBO N = 334"
    },
    {
      "variable": "TAIWAN, PROVINCE OF CHINA",
      "stat": "6 ( 1.8)",
      "colgroup1": "colgroup1",
      "colgroup1_level": "PBO N = 334",
      "colgroup2": "colgroup2",
      "colgroup2_level": "Total N = 670"
    },
    {
      "variable": "TAIWAN, PROVINCE OF CHINA",
      "stat": "16 ( 2.4)",
      "colgroup1": "colgroup1",
      "colgroup1_level": "Total N = 670",
      "colgroup2": "colgroup2",
      "colgroup2_level": ""
    },
    {
      "variable": "REST OF THE WORLD",
      "stat": "1 ( 0.3)",
      "colgroup1": "colgroup1",
      "colgroup1_level": "PBO N = 334",
      "colgroup2": "colgroup2",
      "colgroup2_level": "PBO N = 334"
    },
    {
      "variable": "REST OF THE WORLD",
      "stat": "2 ( 0.6)",
      "colgroup1": "colgroup1",
      "colgroup1_level": "PBO N = 334",
      "colgroup2": "colgroup2",
      "colgroup2_level": "Total N = 670"
    },
    {
      "variable": "REST OF THE WORLD",
      "stat": "3 ( 0.4)",
      "colgroup1": "colgroup1",
      "colgroup1_level": "Total N = 670",
      "colgroup2": "colgroup2",
      "colgroup2_level": ""
    },
    {
      "variable": "AUSTRALIA",
      "stat": "1 ( 0.3)",
      "colgroup1": "colgroup1",
      "colgroup1_level": "PBO N = 334",
      "colgroup2": "colgroup2",
      "colgroup2_level": "PBO N = 334"
    },
    {
      "variable": "AUSTRALIA",
      "stat": "2 ( 0.6)",
      "colgroup1": "colgroup1",
      "colgroup1_level": "PBO N = 334",
      "colgroup2": "colgroup2",
      "colgroup2_level": "Total N = 670"
    },
    {
      "variable": "AUSTRALIA",
      "stat": "3 ( 0.4)",
      "colgroup1": "colgroup1",
      "colgroup1_level": "Total N = 670",
      "colgroup2": "colgroup2",
      "colgroup2_level": ""
    },
    {
      "variable": "Protocol: IM011054",
      "stat": "Protocol: IM011054",
      "colgroup1": "colgroup1",
      "colgroup1_level": "PBO N = 334",
      "colgroup2": "colgroup2",
      "colgroup2_level": "PBO N = 334"
    },
    {
      "variable": "Protocol: IM011054",
      "stat": "Protocol: IM011054Page PAGE of NUMPAGES",
      "colgroup1": "colgroup1",
      "colgroup1_level": "PBO N = 334",
      "colgroup2": "colgroup2",
      "colgroup2_level": "Total N = 670"
    },
    {
      "variable": "Protocol: IM011054",
      "stat": "Protocol: IM011054Page PAGE of NUMPAGES",
      "colgroup1": "colgroup1",
      "colgroup1_level": "Total N = 670",
      "colgroup2": "colgroup2",
      "colgroup2_level": ""
    },
    {
      "variable": "N",
      "stat": "334",
      "colgroup1": "colgroup1",
      "colgroup1_level": "PBO N = 334",
      "colgroup2": "colgroup2",
      "colgroup2_level": "PBO N = 334"
    },
    {
      "variable": "N",
      "stat": "334",
      "colgroup1": "colgroup1",
      "colgroup1_level": "PBO N = 334",
      "colgroup2": "colgroup2",
      "colgroup2_level": "Total N = 670"
    },
    {
      "variable": "N",
      "stat": "668",
      "colgroup1": "colgroup1",
      "colgroup1_level": "Total N = 670",
      "colgroup2": "colgroup2",
      "colgroup2_level": ""
    },
    {
      "variable": "MEAN",
      "stat": "84.22",
      "colgroup1": "colgroup1",
      "colgroup1_level": "PBO N = 334",
      "colgroup2": "colgroup2",
      "colgroup2_level": "PBO N = 334"
    },
    {
      "variable": "MEAN",
      "stat": "82.41",
      "colgroup1": "colgroup1",
      "colgroup1_level": "PBO N = 334",
      "colgroup2": "colgroup2",
      "colgroup2_level": "Total N = 670"
    },
    {
      "variable": "MEAN",
      "stat": "83.31",
      "colgroup1": "colgroup1",
      "colgroup1_level": "Total N = 670",
      "colgroup2": "colgroup2",
      "colgroup2_level": ""
    },
    {
      "variable": "SD",
      "stat": "18.571",
      "colgroup1": "colgroup1",
      "colgroup1_level": "PBO N = 334",
      "colgroup2": "colgroup2",
      "colgroup2_level": "PBO N = 334"
    },
    {
      "variable": "SD",
      "stat": "17.108",
      "colgroup1": "colgroup1",
      "colgroup1_level": "PBO N = 334",
      "colgroup2": "colgroup2",
      "colgroup2_level": "Total N = 670"
    },
    {
      "variable": "SD",
      "stat": "17.864",
      "colgroup1": "colgroup1",
      "colgroup1_level": "Total N = 670",
      "colgroup2": "colgroup2",
      "colgroup2_level": ""
    },
    {
      "variable": "MEDIAN",
      "stat": "83.00",
      "colgroup1": "colgroup1",
      "colgroup1_level": "PBO N = 334",
      "colgroup2": "colgroup2",
      "colgroup2_level": "PBO N = 334"
    },
    {
      "variable": "MEDIAN",
      "stat": "80.40",
      "colgroup1": "colgroup1",
      "colgroup1_level": "PBO N = 334",
      "colgroup2": "colgroup2",
      "colgroup2_level": "Total N = 670"
    },
    {
      "variable": "MEDIAN",
      "stat": "82.05",
      "colgroup1": "colgroup1",
      "colgroup1_level": "Total N = 670",
      "colgroup2": "colgroup2",
      "colgroup2_level": ""
    },
    {
      "variable": "Q1, Q3",
      "stat": "70.80, 95.60",
      "colgroup1": "colgroup1",
      "colgroup1_level": "PBO N = 334",
      "colgroup2": "colgroup2",
      "colgroup2_level": "PBO N = 334"
    },
    {
      "variable": "Q1, Q3",
      "stat": "70.00, 94.00",
      "colgroup1": "colgroup1",
      "colgroup1_level": "PBO N = 334",
      "colgroup2": "colgroup2",
      "colgroup2_level": "Total N = 670"
    },
    {
      "variable": "Q1, Q3",
      "stat": "70.00, 95.25",
      "colgroup1": "colgroup1",
      "colgroup1_level": "Total N = 670",
      "colgroup2": "colgroup2",
      "colgroup2_level": ""
    },
    {
      "variable": "MIN, MAX",
      "stat": "38.5, 138.5",
      "colgroup1": "colgroup1",
      "colgroup1_level": "PBO N = 334",
      "colgroup2": "colgroup2",
      "colgroup2_level": "PBO N = 334"
    },
    {
      "variable": "MIN, MAX",
      "stat": "43.0, 133.6",
      "colgroup1": "colgroup1",
      "colgroup1_level": "PBO N = 334",
      "colgroup2": "colgroup2",
      "colgroup2_level": "Total N = 670"
    },
    {
      "variable": "MIN, MAX",
      "stat": "38.5, 138.5",
      "colgroup1": "colgroup1",
      "colgroup1_level": "Total N = 670",
      "colgroup2": "colgroup2",
      "colgroup2_level": ""
    },
    {
      "variable": "< 90 KG",
      "stat": "220 ( 65.5)",
      "colgroup1": "colgroup1",
      "colgroup1_level": "PBO N = 334",
      "colgroup2": "colgroup2",
      "colgroup2_level": "PBO N = 334"
    },
    {
      "variable": "< 90 KG",
      "stat": "227 ( 68.0)",
      "colgroup1": "colgroup1",
      "colgroup1_level": "PBO N = 334",
      "colgroup2": "colgroup2",
      "colgroup2_level": "Total N = 670"
    },
    {
      "variable": "< 90 KG",
      "stat": "447 ( 66.7)",
      "colgroup1": "colgroup1",
      "colgroup1_level": "Total N = 670",
      "colgroup2": "colgroup2",
      "colgroup2_level": ""
    },
    {
      "variable": ">= 90 KG",
      "stat": "114 ( 33.9)",
      "colgroup1": "colgroup1",
      "colgroup1_level": "PBO N = 334",
      "colgroup2": "colgroup2",
      "colgroup2_level": "PBO N = 334"
    },
    {
      "variable": ">= 90 KG",
      "stat": "107 ( 32.0)",
      "colgroup1": "colgroup1",
      "colgroup1_level": "PBO N = 334",
      "colgroup2": "colgroup2",
      "colgroup2_level": "Total N = 670"
    },
    {
      "variable": ">= 90 KG",
      "stat": "221 ( 33.0)",
      "colgroup1": "colgroup1",
      "colgroup1_level": "Total N = 670",
      "colgroup2": "colgroup2",
      "colgroup2_level": ""
    },
    {
      "variable": "NOT REPORTED",
      "stat": "2 ( 0.6)",
      "colgroup1": "colgroup1",
      "colgroup1_level": "PBO N = 334",
      "colgroup2": "colgroup2",
      "colgroup2_level": "PBO N = 334"
    },
    {
      "variable": "NOT REPORTED",
      "stat": "0",
      "colgroup1": "colgroup1",
      "colgroup1_level": "PBO N = 334",
      "colgroup2": "colgroup2",
      "colgroup2_level": "Total N = 670"
    },
    {
      "variable": "NOT REPORTED",
      "stat": "2 ( 0.3)",
      "colgroup1": "colgroup1",
      "colgroup1_level": "Total N = 670",
      "colgroup2": "colgroup2",
      "colgroup2_level": ""
    },
    {
      "variable": "N",
      "stat": "332",
      "colgroup1": "colgroup1",
      "colgroup1_level": "PBO N = 334",
      "colgroup2": "colgroup2",
      "colgroup2_level": "PBO N = 334"
    },
    {
      "variable": "N",
      "stat": "334",
      "colgroup1": "colgroup1",
      "colgroup1_level": "PBO N = 334",
      "colgroup2": "colgroup2",
      "colgroup2_level": "Total N = 670"
    },
    {
      "variable": "N",
      "stat": "666",
      "colgroup1": "colgroup1",
      "colgroup1_level": "Total N = 670",
      "colgroup2": "colgroup2",
      "colgroup2_level": ""
    },
    {
      "variable": "MEAN",
      "stat": "30.26",
      "colgroup1": "colgroup1",
      "colgroup1_level": "PBO N = 334",
      "colgroup2": "colgroup2",
      "colgroup2_level": "PBO N = 334"
    },
    {
      "variable": "MEAN",
      "stat": "29.61",
      "colgroup1": "colgroup1",
      "colgroup1_level": "PBO N = 334",
      "colgroup2": "colgroup2",
      "colgroup2_level": "Total N = 670"
    },
    {
      "variable": "MEAN",
      "stat": "29.94",
      "colgroup1": "colgroup1",
      "colgroup1_level": "Total N = 670",
      "colgroup2": "colgroup2",
      "colgroup2_level": ""
    },
    {
      "variable": "SD",
      "stat": "6.391",
      "colgroup1": "colgroup1",
      "colgroup1_level": "PBO N = 334",
      "colgroup2": "colgroup2",
      "colgroup2_level": "PBO N = 334"
    },
    {
      "variable": "SD",
      "stat": "5.617",
      "colgroup1": "colgroup1",
      "colgroup1_level": "PBO N = 334",
      "colgroup2": "colgroup2",
      "colgroup2_level": "Total N = 670"
    },
    {
      "variable": "SD",
      "stat": "6.019",
      "colgroup1": "colgroup1",
      "colgroup1_level": "Total N = 670",
      "colgroup2": "colgroup2",
      "colgroup2_level": ""
    },
    {
      "variable": "MEDIAN",
      "stat": "29.40",
      "colgroup1": "colgroup1",
      "colgroup1_level": "PBO N = 334",
      "colgroup2": "colgroup2",
      "colgroup2_level": "PBO N = 334"
    },
    {
      "variable": "MEDIAN",
      "stat": "29.19",
      "colgroup1": "colgroup1",
      "colgroup1_level": "PBO N = 334",
      "colgroup2": "colgroup2",
      "colgroup2_level": "Total N = 670"
    },
    {
      "variable": "MEDIAN",
      "stat": "29.30",
      "colgroup1": "colgroup1",
      "colgroup1_level": "Total N = 670",
      "colgroup2": "colgroup2",
      "colgroup2_level": ""
    },
    {
      "variable": "Q1, Q3",
      "stat": "26.10, 33.94",
      "colgroup1": "colgroup1",
      "colgroup1_level": "PBO N = 334",
      "colgroup2": "colgroup2",
      "colgroup2_level": "PBO N = 334"
    },
    {
      "variable": "Q1, Q3",
      "stat": "25.78, 32.58",
      "colgroup1": "colgroup1",
      "colgroup1_level": "PBO N = 334",
      "colgroup2": "colgroup2",
      "colgroup2_level": "Total N = 670"
    },
    {
      "variable": "Q1, Q3",
      "stat": "25.95, 33.15",
      "colgroup1": "colgroup1",
      "colgroup1_level": "Total N = 670",
      "colgroup2": "colgroup2",
      "colgroup2_level": ""
    },
    {
      "variable": "MIN, MAX",
      "stat": "15.6, 57.2",
      "colgroup1": "colgroup1",
      "colgroup1_level": "PBO N = 334",
      "colgroup2": "colgroup2",
      "colgroup2_level": "PBO N = 334"
    },
    {
      "variable": "MIN, MAX",
      "stat": "17.0, 46.2",
      "colgroup1": "colgroup1",
      "colgroup1_level": "PBO N = 334",
      "colgroup2": "colgroup2",
      "colgroup2_level": "Total N = 670"
    },
    {
      "variable": "MIN, MAX",
      "stat": "15.6, 57.2",
      "colgroup1": "colgroup1",
      "colgroup1_level": "Total N = 670",
      "colgroup2": "colgroup2",
      "colgroup2_level": ""
    }
  ],
  "metadata": {
    "source_file": "rt-dm-demo-backup.rtf",
    "parser": "RTF row-based parser with hierarchical support",
    "timestamp": "2025-07-10 11:51:52",
    "title": "Table 14.1.3.1 Demographic and Baseline Characteristics Summary Randomized Population",
    "footnotes": "BMI = Body Mass Index. Age presented is age at date of informed consent. Program Path: BMS_GBS Program Name: rt-dm-demo.sas 12DEC2024:06:43:38"
  }
}
